Workbook

Sheet Cover 

Sheet Transaction Assumptions
A1: ExxonMobil–Pioneer Transaction Assumptions
A4: All figures in $ millions, except per-share data
A5: Transaction Detail | B5: Value
A6: Acquirer | B6: ExxonMobil
A7: Target | B7: Pioneer Natural Resources
A8: Transaction Type | B8: 100% Stock
A9: Announced Equity Value | B9: 59500
A10: Exchange Ratio | B10: 2.3234x
A11: Pioneer Unaffected Share Price | B11: 214.96
A12: Implied Offer Price | B12: 253.23
A13: Acquisition Premium | B13: 0.178
A18: Share Issuance
A20: All figures in $ millions, except per-share data
A21: Share Calculation | B21: Value
A22: Pioneer Fully Diluted Shares | B22: 234.7
A23: Exchange Ratio | B23: 2.3234x
A24: New Exxon Shares Issued | B24: 545.2
A25: Existing Exxon Shares | B25: 4052
A26: Pro Forma Exxon Shares | B26: 4597.2
A27: Pioneer Shareholders’ Ownership | B27: 0.119
A32: Synergy Assumptions
A34: All figures in $ millions, except per-share data
A35: Synergy Detail | B35: Value
A36: Year 2 Synergies | B36: 1000
A37: Long-Term Average Annual Synergies | B37: 2000
A38: Improved Resource Recovery | B38: 1300
A39: Capital and Operating Cost Savings | B39: 700

Sheet ExxonMobil Financials
A1: ExxonMobil Standalone Financials
A2: Historical results and standalone projections before the Pioneer acquisition
A3: All figures in $ millions, except per-share data
A4: Metric | B4: 2021A | C4: 2022A | D4: 2023A | E4: 2024E | F4: 2025E | G4: 2026E
A5: Total Revenue | B5: 285640 | C5: 413680 | D5: 344582 | E5: =D5*(1+B15) -> 351473.64 | F5: =E5*(1+C15) -> 358503.11 | G5: =F5*(1+D15) -> 365673.18
A6: Income Before Taxes | B6: 31234 | C6: 77753 | D6: 52783 | E6: =E5*B16 -> 53775.467 | F6: =F5*C16 -> 54850.976 | G6: =G5*D16 -> 55947.996
A7: Income Tax Expense | B7: 7636 | C7: 20176 | D7: 15429 | E7: =E6*B17 -> 15702.436 | F7: =F6*C17 -> 16016.485 | G7: =G6*D17 -> 16336.815
A8: Net Income | B8: 23040 | C8: 55740 | D8: 36010 | E8: =(E6-E7)*(1-B18) -> 36702.401 | F8: =(F6-F7)*(1-C18) -> 37436.45 | G8: =(G6-G7)*(1-D18) -> 38185.178
A9: Diluted Shares Outstanding | B9: 4275 | C9: 4205 | D9: 4052 | E9: =D9*(1-B19) -> 3970.96 | F9: =E9*(1-C19) -> 3891.5408 | G9: =F9*(1-D19) -> 3813.71
A10: Earnings Per Share | B10: 5.39 | C10: 13.26 | D10: 8.89 | E10: =E8/E9 -> 9.2427024 | F10: =F8/F9 -> 9.6199555 | G10: =G8/G9 -> 10.012607
A12: ExxonMobil Forecast Assumptions
A13: All figures in $ millions, except per-share data
A14: Forecast Assumption | B14: 2024E | C14: 2025E | D14: 2026E
A15: Revenue Growth | B15: 0.02 | C15: 0.02 | D15: 0.02
A16: Pretax Margin | B16: 0.153 | C16: 0.153 | D16: 0.153
A17: Effective Tax Rate | B17: 0.292 | C17: 0.292 | D17: 0.292
A18: Noncontrolling Interest % | B18: 0.036 | C18: 0.036 | D18: 0.036
A19: Annual Share Reduction | B19: 0.02 | C19: 0.02 | D19: 0.02

Sheet Pioneer Financials
A1: Pioneer Natural Resources Standalone Financials
A3: Figures in $ millions, except EPS.
A4: Metric | B4: 2021A | C4: 2022A | D4: 2023A | E4: 2024E | F4: 2025E | G4: 2026E
A5: Total Revenue | B5: 14643 | C5: 24294 | D5: 19362 | E5: =D5*(1+B18) -> 22092.042 | F5: =E5*(1+C18) -> 21628.109 | G5: =F5*(1+D18) -> 21476.712
A6: Income Before Taxes | B6: 2746 | C6: 9951 | D6: 6247 | E6: =E5*B20 -> 8019.4112 | F6: =F5*C20 -> 7483.3258 | G6: =G5*D20 -> 7065.8384
A7: Income Tax Expense | B7: 628 | C7: 2106 | D7: 1353 | E7: =E6*B21 -> 1740.2122 | F7: =F6*C21 -> 1623.8817 | G7: =G6*D21 -> 1533.2869
A8: Net Income | B8: 2118 | C8: 7845 | D8: 4894 | E8: =E6-E7 -> 6279.199 | F8: =F6-F7 -> 5859.4441 | G8: =G6-G7 -> 5532.5514
A9: Diluted Shares Outstanding | B9: 246 | C9: 252 | D9: 242 | E9: =D9*(1-B22) -> 234.74 | F9: =E9*(1-C22) -> 234.74 | G9: =F9*(1-D22) -> 234.74
A10: Earnings Per Share | B10: 8.61 | C10: 31.13 | D10: 20.21 | E10: =E8/E9 -> 26.749591 | F10: =F8/F9 -> 24.961421 | G10: =G8/G9 -> 23.568848
A15: Forecast Assumptions
A17: Forecast Assumption | B17: 2024E | C17: 2025E | D17: 2026E
A18: Revenue Growth | B18: 0.141 | C18: -0.021 | D18: -0.007
A19: Production Growth | B19: 0.08 | C19: 0.071 | D19: 0.069
A20: Pretax Margin | B20: 0.363 | C20: 0.346 | D20: 0.329
A21: Effective Tax Rate | B21: 0.217 | C21: 0.217 | D21: 0.217
A22: Annual Share Reduction | B22: 0.03 | C22: 0 | D22: 0

Sheet Accretion Dilution Analysis
A1: Accretion/Dilution Analysis
A3: Figures in $ millions, except per-share data.
A4: Metric | B4: 2024E | C4: 2025E | D4: 2026E
A5: ExxonMobil Standalone Net Income | B5: ='ExxonMobil Financials'!E8 -> 36702.401 | C5: ='ExxonMobil Financials'!F8 -> 37436.45 | D5: ='ExxonMobil Financials'!G8 -> 38185.178
A6: Pioneer Standalone Net Income | B6: ='Pioneer Financials'!E8 -> 6279.199 | C6: ='Pioneer Financials'!F8 -> 5859.4441 | D6: ='Pioneer Financials'!G8 -> 5532.5514
A7: Pretax Synergies | B7: =B29 -> 0 | C7: =C29 -> 500 | D7: =D29 -> 1000
A8: Synergy Tax Rate | B8: =B30 -> 0.292 | C8: =C30 -> 0.292 | D8: =D30 -> 0.292
A9: After-Tax Synergies | B9: =B7*(1-B8) -> 0 | C9: =C7*(1-C8) -> 354 | D9: =D7*(1-D8) -> 708
A10: Pro Forma Combined Net Income | B10: =B5+B6+B9 -> 42981.6 | C10: =C5+C6+C9 -> 43649.894 | D10: =D5+D6+D9 -> 44425.73
A11: ExxonMobil Standalone Diluted Shares | B11: ='ExxonMobil Financials'!E9 -> 3970.96 | C11: ='ExxonMobil Financials'!F9 -> 3891.5408 | D11: ='ExxonMobil Financials'!G9 -> 3813.71
A12: New ExxonMobil Shares Issued | B12: =B27*'Pioneer Financials'!E9 -> 545.39492 | C12: =C27*'Pioneer Financials'!F9 -> 545.39492 | D12: =D27*'Pioneer Financials'!G9 -> 545.39492
A13: Pro Forma Diluted Shares | B13: =B11+B12 -> 4516.3549 | C13: =C11+C12 -> 4436.9357 | D13: =D11+D12 -> 4359.1049
A14: ExxonMobil Standalone EPS | B14: =B5/B11 -> 9.2427024 | C14: =C5/C11 -> 9.6199555 | D14: =D5/D11 -> 10.012607
A15: Pro Forma Combined EPS | B15: =B10/B13 -> 9.5168784 | C15: =C10/C13 -> 9.8378467 | D15: =D10/D13 -> 10.19148
A16: EPS Accretion / (Dilution) | B16: =(B15/B14)-1 -> 0.029664051 | C16: =(C15/C14)-1 -> 0.022649917 | D16: =(D15/D14)-1 -> 0.017864788
A22: Accretion/Dilution Assumptions
A24: Figures in $ millions, except per-share data.
A25: Assumption | B25: 2024E | C25: 2025E | D25: 2026E
A26: Pioneer Diluted Shares | B26: 234.7 | C26: 234.7 | D26: 234.7
A27: Exchange Ratio (x) | B27: 2.3234 | C27: 2.3234 | D27: 2.3234
A28: New Exxon Shares Issued | B28: 545.2 | C28: 545.2 | D28: 545.2
A29: Pretax Synergies | B29: 0 | C29: 500 | D29: 1000
A30: Synergy Tax Rate | B30: 0.292 | C30: 0.292 | D30: 0.292
A31: Transaction Financing | B31: 100% Stock | C31: 100% Stock | D31: 100% Stock

Sheet Accretion Dilution Sensitivity
A1: ExxonMobil–Pioneer 2026E Accretion/Dilution Sensitivity Base-Case Inputs
A4: Figures in $ millions, except per-share data.
A5: Base-Case Metric | B5: 2026E Value | C5: Purpose
A6: Exxon Standalone Net Income | B6: 38185.2 | C6: Exxon earnings without Pioneer
A7: Pioneer Standalone Net Income | B7: 5532.6 | C7: Base earnings contributed by Pioneer
A8: Exxon Standalone Shares | B8: 3814 | C8: Existing Exxon share count
A9: New Shares Issued | B9: 545.2 | C9: Shares issued to Pioneer investors
A10: Pro Forma Shares | B10: 4359.2 | C10: Total shares following the acquisition
A11: Synergy Tax Rate | B11: 0.292 | C11: Converts pretax synergies into after-tax earnings
A12: Exxon Standalone EPS | B12: 10.01 | C12: Benchmark used to measure accretion
A13: Base Pretax Synergies | B13: 1000 | C13: Expected full-year synergies
A17: 2026E EPS Accretion/(Dilution) Sensitivity
A19: Figures in $ millions, except per-share data.
A20: =B30 -> 0.018109254 | B20: 0 | C20: 500 | D20: 1000 | E20: 1500 | F20: 2000
A21: 4426.1 | B21: -0.0237 | C21: -0.0155 | D21: -0.0074 | E21: 0.0007 | F21: 0.0088
A22: 4979.3 | B22: -0.011 | C22: -0.0029 | D22: 0.5%2 | E22: 0.0134 | F22: 0.0215
A23: 5532.6 | B23: 0.0017 | C23: 0.0098 | D23: 0.0179 | E23: 0.026 | F23: 0.0341
A24: 6085.9 | B24: 0.0144 | C24: 0.0225 | D24: 0.0306 | E24: 0.0387 | F24: 0.0468
A25: 6639.1 | B25: 0.0271 | C25: 0.0352 | D25: 0.0514 | E25: 0.0514 | F25: 0.0595
A27: Sensitivity Driver | B27: Value
A28: Pioneer Net Income Input | B28: 5532.6
A29: Pretax Synergy Input | B29: 1000
A30: EPS Accretion/(Dilution) Output | B30: =(((38185.2+B7+B29*(1-B11))/B10)/B12)-1 -> 0.018109254

Sheet Executive Summary 1
A1: ExxonMobil–Pioneer Natural Resources Acquisition | J1: Accretion/Dilution Forecast
J3: Figures in $ millions, except per-share data
A4: Figures in $ millions, except per-share data | J4: Financial Metric | K4: 2024E | L4: 2025E | M4: 2026E
A5: Transaction Overview | J5: Exxon Standalone Net Income | K5: 36702.4 | L5: 37436.4 | M5: 38185.2
A6: Transaction Metric | B6: Value | C6: Description | J6: Pioneer Standalone Net Income | K6: 6279.2 | L6: 5859.4 | M6: 5532.6
A7: Acquirer | B7: ExxonMobil | C7: Buyer | J7: Pretax Synergies | K7: 0 | L7: 500 | M7: 1000
A8: Target | B8: Pioneer Natural Resources | C8: Company acquired | J8: Synergy Tax Rate | K8: 0.292 | L8: 0.292 | M8: 0.292
A9: Transaction Type | B9: 100% Stock | C9: No cash consideration | J9: After-Tax Synergies | K9: 0 | L9: 354 | M9: 708
A10: Equity Value | B10: 59500 | C10: Total value paid for Pioneer equity | J10: Pro Forma Combined Net Income | K10: 42981.6 | L10: 43649.8 | M10: 44425.8
A11: Exchange Ratio | B11: 2.32x | C11: Exxon shares issued for each Pioneer share | J11: Exxon Standalone Shares | K11: 3971 | L11: 3892 | M11: 3814
A12: Pioneer Unaffected Price | B12: 215 | C12: Share price before the acquisition announcement | J12: New Shares Issued | K12: 545.2 | L12: 545.2 | M12: 545.2
A13: Implied Offer Price | B13: 253.2 | C13: Value received per Pioneer share | J13: Pro Forma Shares | K13: 4516.2 | L13: 4437.2 | M13: 4359.2
A14: Acquisition Premium | B14: 0.178 | C14: Premium over Pioneer’s unaffected price | J14: Exxon Standalone EPS | K14: 9.24 | L14: 9.62 | M14: 10.01
A15: Pioneer Diluted Shares | B15: 234.7 | C15: Pioneer shares converted into Exxon shares | J15: Pro Forma EPS | K15: 9.52 | L15: 9.84 | M15: 10.19
A16: New Exxon Shares Issued | B16: 545.2 | C16: Shares issued to Pioneer investors | J16: EPS Accretion/(Dilution) | K16: 0.0295 | L16: 0.0227 | M16: 0.0179
A17: Existing Exxon Shares | B17: 4052 | C17: Exxon shares before the acquisition
A18: Pro Forma Shares at Closing | B18: 4597.2 | C18: Combined share count at transaction closing
A19: Pioneer Ownership | B19: 0.119 | C19: Combined company owned by former Pioneer investors
G26: Strategic Rationale and Key Risks
A27: 2026E Sensitivity Summary
A28: Figures in $ millions, except per-share data | G28: Figures in $ millions, except per-share data
A29: Sensitivity Metric | B29: Result | G29: Category | H29: Factor | I29: Explanation
A30: Worst-Case EPS Accretion/(Dilution) | B30: -0.0237 | G30: Strategic Rationale | H30: Permian Basin Scale | I30: Expands Exxon’s position and production capacity in the Permian Basin
A31: Base-Case EPS Accretion | B31: 0.0179 | G31: Strategic Rationale | H31: Operational Efficiencies | I31: Combines drilling, infrastructure, logistics and purchasing operations
A32: Best-Case EPS Accretion | B32: 0.0595 | G32: Strategic Rationale | H32: Resource Inventory | I32: Adds long-life, high-quality oil and gas production assets
A33: Pioneer Net Income Range | B33: $4,426.1m–$6,639.1m | G33: Strategic Rationale | H33: Improved Recovery | I33: Exxon expects technology to increase production and resource recovery
A34: Pretax Synergy Range | B34: $0m–$2,000m | G34: Strategic Rationale | H34: Synergy Potential | I34: Produces near-term savings with up to $2 billion of longer-term potential
A35: Base Pioneer NI With No Synergies | B35: 0.17% accretive | G35: Key Risk | H35: Commodity Prices | I35: Lower oil and natural-gas prices could reduce Pioneer’s earnings
A36: Synergies Needed With Pioneer 10% Below Forecast | B36: Approximately $677m | G36: Key Risk | H36: Integration Execution | I36: Delays or operational problems could prevent synergy realization
A37: Synergies Needed With Pioneer 20% Below Forecast | B37: Approximately $1,458m | G37: Key Risk | H37: Share Dilution | I37: Exxon issued 545.2 million shares to complete the acquisition
G38: Key Risk | H38: Earnings Underperformance | I38: The transaction can become dilutive if Pioneer earnings fall sufficiently
G39: Key Risk | H39: Valuation Risk | I39: EPS accretion does not necessarily mean Exxon received more value than it paid

Sheet Executive Summary 2
A2: Overall Deal Conclusion | E2: Overall Deal Conclusion
A5: Conclusion Metric | B5: Assessment
A6: Base-Case Result | B6: Acquisition is projected to be 1.79% EPS accretive in 2026E
A7: Downside Protection | B7: Deal remains slightly accretive at base Pioneer earnings without synergies
A8: Primary Value Driver | B8: Pioneer’s future net income and operating performance
A9: Secondary Value Driver | B9: Exxon’s ability to realize projected synergies
A10: Overall Assessment | B10: Moderately accretive transaction with additional upside from stronger Pioneer earnings and synergy realization

Sheet Power Bi Dashboard 1
A2: Column1 | B2: Column2 | C2: Column3 | D2: Column4
A3: 1. Transaction_Summary
A5: Category | B5: Metric | C5: Value | D5: Unit
A6: Deal Terms | B6: Announced Equity Value | C6: 59500 | D6: $ millions
A7: Deal Terms | B7: Exchange Ratio | C7: 2.3234 | D7: x
A8: Deal Terms | B8: Pioneer Unaffected Share Price | C8: 214.96 | D8: $ per share
A9: Deal Terms | B9: Implied Offer Price | C9: 253.23 | D9: $ per share
A10: Deal Terms | B10: Acquisition Premium | C10: 0.178 | D10: Percentage
A11: Share Issuance | B11: Pioneer Diluted Shares | C11: 234.7 | D11: Million shares
A12: Share Issuance | B12: New Exxon Shares Issued | C12: 545.2 | D12: Million shares
A13: Share Issuance | B13: Existing Exxon Shares | C13: 4052 | D13: Million shares
A14: Share Issuance | B14: Pro Forma Exxon Shares | C14: 4597.2 | D14: Million shares
A15: Share Issuance | B15: Pioneer Ownership | C15: 0.119 | D15: Percentage
A16: Synergies | B16: Year 2 Synergies | C16: 1000 | D16: $ millions
A17: Synergies | B17: Long-Term Annual Synergies | C17: 2000 | D17: $ millions

Sheet Power Bi DashBoard 2
A1: 2. Financial_Performance | B1: Column1 | C1: Column2 | D1: Column3 | E1: Column4 | F1: Column5
A3: Company | B3: Period | C3: Period Type | D3: Revenue ($m) | E3: Net Income ($m) | F3: EPS ($)
A4: ExxonMobil | B4: 2021A | C4: Actual | D4: 285640 | E4: 23040 | F4: 5.39
A5: ExxonMobil | B5: 2022A | C5: Actual | D5: 413680 | E5: 55740 | F5: 13.26
A6: ExxonMobil | B6: 2023A | C6: Actual | D6: 344582 | E6: 36010 | F6: 8.89
A7: ExxonMobil | B7: 2024E | C7: Estimate | D7: 351473.6 | E7: 36702.4 | F7: 9.24
A8: ExxonMobil | B8: 2025E | C8: Estimate | D8: 358503.1 | E8: 37436.4 | F8: 9.62
A9: ExxonMobil | B9: 2026E | C9: Estimate | D9: 365673.2 | E9: 38185.2 | F9: 10.01
A10: Pioneer | B10: 2021A | C10: Actual | D10: 14643 | E10: 2118 | F10: 8.61
A11: Pioneer | B11: 2022A | C11: Actual | D11: 24294 | E11: 7845 | F11: 31.13
A12: Pioneer | B12: 2023A | C12: Actual | D12: 19362 | E12: 4894 | F12: 20.21
A13: Pioneer | B13: 2024E | C13: Estimate | D13: 22092 | E13: 6279.2 | F13: 26.75
A14: Pioneer | B14: 2025E | C14: Estimate | D14: 21628.1 | E14: 5859.4 | F14: 24.96
A15: Pioneer | B15: 2026E | C15: Estimate | D15: 21476.7 | E15: 5532.6 | F15: 23.57

Sheet Power Bi Dashboard 3
A1: 3. Accretion_Dilution | B1: Column1 | C1: Column2 | D1: Column3 | E1: Column4 | F1: Column5 | G1: Column6 | H1: Column7 | I1: Column8
A3: Period | B3: Exxon NI ($m) | C3: Pioneer NI ($m) | D3: Pretax Synergies ($m) | E3: After-Tax Synergies ($m) | F3: Pro Forma NI ($m) | G3: Standalone EPS ($) | H3: Pro Forma EPS ($) | I3: Accretion (%)
A4: 2024E | B4: 36702.4 | C4: 6279.2 | D4: 0 | E4: 0 | F4: 42981.6 | G4: 9.24 | H4: 9.52 | I4: 0.0297
A5: 2025E | B5: 37436.4 | C5: 5859.4 | D5: 500 | E5: 354 | F5: 43649.9 | G5: 9.62 | H5: 9.84 | I5: 0.0226
A6: 2026E | B6: 38185.2 | C6: 5532.6 | D6: 1000 | E6: 708 | F6: 44425.7 | G6: 10.01 | H6: 10.19 | I6: 0.0179

Sheet Power Bi Dashboard 4
A3: Sensitivity | B3: Column1 | C3: Column2 | D3: Column3 | E3: Column4 | F3: Column5
A5: The columns represent pretax synergies in $ millions.
A7: Pioneer Net Income ($m) | B7: Synergies: 0 | C7: Synergies: 500 | D7: Synergies: 1000 | E7: Synergies: 1500 | F7: Synergies: 2000
A8: 4426.1 | B8: -0.0237 | C8: -0.0155 | D8: -0.0074 | E8: 0.0007 | F8: 0.0088
A9: 4979.3 | B9: -0.011 | C9: -0.0029 | D9: 0.0052 | E9: 0.0134 | F9: 0.0215
A10: 5532.6 | B10: 0.0017 | C10: 0.0098 | D10: 0.0179 | E10: 0.026 | F10: 0.0341
A11: 6085.9 | B11: 0.0144 | C11: 0.0225 | D11: 0.0306 | E11: 0.0387 | F11: 0.0468
A12: 6639.1 | B12: 0.0271 | C12: 0.0352 | D12: 0.0433 | E12: 0.0514 | F12: 0.0595
